{
    "openapi": "3.1.1",
    "info": {
        "title": "Parking Pass API",
        "version": "1.0.0",
        "summary": "주차장 입출차 관리 API",
        "description": "번호판 인식 기반 주차장 입출차 관리 시스템",
        "license": "Apache/2.0"
    },
    "paths": {
        "/api/v1/auth/register": {
            "post": {
                "requestBody": {
                    "description": "",
                    "content": {
                        "application/json": {
                            "schema": {
                                "$ref": "#/components/schemas/RegisterRequest"
                            }
                        }
                    }
                },
                "responses": {
                    "201": {
                        "description": "",
                        "content": {
                            "application/json": {
                                "schema": {
                                    "$ref": "#/components/schemas/AuthResponse"
                                }
                            }
                        }
                    }
                }
            }
        },
        "/api/v1/auth/login": {
            "post": {
                "requestBody": {
                    "description": "",
                    "content": {
                        "application/json": {
                            "schema": {
                                "$ref": "#/components/schemas/LoginRequest"
                            }
                        }
                    }
                },
                "responses": {
                    "200": {
                        "description": "",
                        "content": {
                            "application/json": {
                                "schema": {
                                    "$ref": "#/components/schemas/AuthResponse"
                                }
                            }
                        }
                    }
                }
            }
        },
        "/api/v1/auth/oauth/kakao": {
            "post": {
                "requestBody": {
                    "description": "",
                    "content": {
                        "application/json": {
                            "schema": {
                                "$ref": "#/components/schemas/KakaoLoginRequest"
                            }
                        }
                    }
                },
                "responses": {
                    "200": {
                        "description": "",
                        "content": {
                            "application/json": {
                                "schema": {
                                    "$ref": "#/components/schemas/AuthResponse"
                                }
                            }
                        }
                    }
                }
            }
        },
        "/api/v1/auth/me": {
            "get": {
                "security": [
                    {
                        "auth-jwt": []
                    }
                ],
                "responses": {
                    "200": {
                        "description": "",
                        "content": {
                            "application/json": {
                                "schema": {
                                    "$ref": "#/components/schemas/UserResponse"
                                }
                            }
                        }
                    }
                }
            }
        },
        "/api/v1/gates": {
            "get": {
                "summary": "게이트 목록 조회 (ADMIN 이상)",
                "security": [
                    {
                        "auth-jwt": []
                    }
                ],
                "parameters": [
                    {
                        "name": "parkingLotId",
                        "in": "query",
                        "required": false,
                        "schema": {
                            "type": "string"
                        }
                    }
                ],
                "responses": {
                    "200": {
                        "description": "",
                        "content": {
                            "application/json": {
                                "schema": {
                                    "type": "array",
                                    "items": {
                                        "$ref": "#/components/schemas/GateResponse"
                                    }
                                }
                            }
                        }
                    }
                }
            }
        },
        "/api/v1/gates/register": {
            "post": {
                "summary": "게이트 등록 (ADMIN 이상)",
                "security": [
                    {
                        "auth-jwt": []
                    }
                ],
                "requestBody": {
                    "description": "",
                    "content": {
                        "application/json": {
                            "schema": {
                                "$ref": "#/components/schemas/RegisterGateRequest"
                            }
                        }
                    }
                },
                "responses": {
                    "201": {
                        "description": "",
                        "content": {
                            "application/json": {
                                "schema": {
                                    "$ref": "#/components/schemas/GateResponse"
                                }
                            }
                        }
                    }
                }
            }
        },
        "/api/v1/health": {
            "get": {
                "summary": "HealthCheck",
                "requestBody": {
                    "description": "HealthCheck 요청",
                    "content": {
                        "application/json": {}
                    }
                },
                "responses": {
                    "200": {
                        "description": "HealthCheck 성공 응답",
                        "content": {
                            "application/json": {
                                "schema": {
                                    "type": "string"
                                }
                            }
                        }
                    }
                },
                "tags": [
                    "Health"
                ]
            }
        },
        "/api/v1/events/plate-detected": {
            "post": {
                "summary": "번호판 인식 이벤트 처리",
                "requestBody": {
                    "description": "PlateDetectedRequest 번호판 인식 요청",
                    "content": {
                        "application/json": {
                            "schema": {
                                "$ref": "#/components/schemas/PlateDetectedRequest"
                            }
                        }
                    }
                },
                "responses": {
                    "200": {
                        "description": "PlateDetectedResponse 성공 응답",
                        "content": {
                            "application/json": {
                                "schema": {
                                    "$ref": "#/components/schemas/PlateDetectedResponse"
                                }
                            }
                        }
                    }
                },
                "tags": [
                    "ParkingEvents"
                ]
            }
        },
        "/api/v1/parking-lots": {
            "post": {
                "summary": "주차장 등록 (인증 필요)",
                "security": [
                    {
                        "auth-jwt": []
                    }
                ],
                "requestBody": {
                    "description": "",
                    "content": {
                        "application/json": {
                            "schema": {
                                "$ref": "#/components/schemas/CreateParkingLotRequest"
                            }
                        }
                    }
                },
                "responses": {
                    "201": {
                        "description": "",
                        "content": {
                            "application/json": {
                                "schema": {
                                    "$ref": "#/components/schemas/ParkingLotResponse"
                                }
                            }
                        }
                    }
                }
            },
            "get": {
                "summary": "주차장 목록 조회",
                "responses": {
                    "200": {
                        "description": "List<ParkingLotResponse> 주차장 목록",
                        "content": {
                            "application/json": {
                                "schema": {
                                    "type": "array",
                                    "items": {
                                        "$ref": "#/components/schemas/ParkingLotResponse"
                                    }
                                }
                            }
                        }
                    }
                },
                "tags": [
                    "ParkingLots"
                ]
            }
        },
        "/api/v1/parking-lots/my-lots": {
            "get": {
                "summary": "내가 속한 주차장 목록",
                "security": [
                    {
                        "auth-jwt": []
                    }
                ],
                "responses": {
                    "200": {
                        "description": "",
                        "content": {
                            "application/json": {
                                "schema": {
                                    "type": "array",
                                    "items": {
                                        "$ref": "#/components/schemas/ParkingLotResponse"
                                    }
                                }
                            }
                        }
                    }
                }
            }
        },
        "/api/v1/parking-lots/search": {
            "get": {
                "summary": "공개 주차장 검색",
                "parameters": [
                    {
                        "name": "[String]",
                        "in": "query",
                        "description": "q 검색어",
                        "required": false,
                        "schema": {
                            "type": "string"
                        }
                    },
                    {
                        "name": "q",
                        "in": "query",
                        "required": false,
                        "schema": {
                            "type": "string"
                        }
                    }
                ],
                "responses": {
                    "200": {
                        "description": "",
                        "content": {
                            "application/json": {
                                "schema": {
                                    "type": "array",
                                    "items": {
                                        "$ref": "#/components/schemas/ParkingLotResponse"
                                    }
                                }
                            }
                        }
                    }
                }
            }
        },
        "/api/v1/parking-lots/{id}": {
            "get": {
                "summary": "주차장 조회",
                "parameters": [
                    {
                        "name": "[Long]",
                        "in": "path",
                        "description": "id 주차장 ID",
                        "required": true,
                        "schema": {
                            "type": "string"
                        }
                    },
                    {
                        "name": "id",
                        "in": "path",
                        "required": true,
                        "schema": {
                            "type": "string"
                        }
                    }
                ],
                "responses": {
                    "200": {
                        "description": "ParkingLotResponse 주차장 정보",
                        "content": {
                            "application/json": {
                                "schema": {
                                    "$ref": "#/components/schemas/ParkingLotResponse"
                                }
                            }
                        }
                    }
                },
                "tags": [
                    "ParkingLots"
                ]
            }
        },
        "/api/v1/parking-lots/{parkingLotId}/members": {
            "get": {
                "security": [
                    {
                        "auth-jwt": []
                    }
                ],
                "parameters": [
                    {
                        "name": "parkingLotId",
                        "in": "path",
                        "required": true,
                        "schema": {
                            "type": "string"
                        }
                    }
                ],
                "responses": {
                    "200": {
                        "description": "",
                        "content": {
                            "application/json": {
                                "schema": {
                                    "type": "array",
                                    "items": {
                                        "$ref": "#/components/schemas/ParkingLotMemberResponse"
                                    }
                                }
                            }
                        }
                    }
                }
            }
        },
        "/api/v1/parking-lots/{parkingLotId}/members/join-request": {
            "post": {
                "security": [
                    {
                        "auth-jwt": []
                    }
                ],
                "parameters": [
                    {
                        "name": "parkingLotId",
                        "in": "path",
                        "required": true,
                        "schema": {
                            "type": "string"
                        }
                    }
                ],
                "responses": {
                    "200": {
                        "description": "",
                        "content": {
                            "application/json": {
                                "schema": {
                                    "$ref": "#/components/schemas/ParkingLotMemberResponse"
                                }
                            }
                        }
                    }
                }
            }
        },
        "/api/v1/parking-lots/{parkingLotId}/members/invite": {
            "post": {
                "security": [
                    {
                        "auth-jwt": []
                    }
                ],
                "parameters": [
                    {
                        "name": "parkingLotId",
                        "in": "path",
                        "required": true,
                        "schema": {
                            "type": "string"
                        }
                    }
                ],
                "requestBody": {
                    "description": "",
                    "content": {
                        "application/json": {
                            "schema": {
                                "$ref": "#/components/schemas/InviteMemberRequest"
                            }
                        }
                    }
                },
                "responses": {
                    "201": {
                        "description": "",
                        "content": {
                            "application/json": {
                                "schema": {
                                    "$ref": "#/components/schemas/ParkingLotMemberResponse"
                                }
                            }
                        }
                    }
                }
            }
        },
        "/api/v1/parking-lots/{parkingLotId}/members/{userId}/approve": {
            "put": {
                "security": [
                    {
                        "auth-jwt": []
                    }
                ],
                "parameters": [
                    {
                        "name": "parkingLotId",
                        "in": "path",
                        "required": true,
                        "schema": {
                            "type": "string"
                        }
                    },
                    {
                        "name": "userId",
                        "in": "path",
                        "required": true,
                        "schema": {
                            "type": "string"
                        }
                    }
                ],
                "responses": {
                    "200": {
                        "description": "",
                        "content": {
                            "application/json": {
                                "schema": {
                                    "$ref": "#/components/schemas/ParkingLotMemberResponse"
                                }
                            }
                        }
                    }
                }
            }
        },
        "/api/v1/parking-lots/{parkingLotId}/members/{userId}/reject": {
            "put": {
                "security": [
                    {
                        "auth-jwt": []
                    }
                ],
                "parameters": [
                    {
                        "name": "parkingLotId",
                        "in": "path",
                        "required": true,
                        "schema": {
                            "type": "string"
                        }
                    },
                    {
                        "name": "userId",
                        "in": "path",
                        "required": true,
                        "schema": {
                            "type": "string"
                        }
                    }
                ],
                "responses": {
                    "200": {
                        "description": "",
                        "content": {
                            "application/json": {
                                "schema": {
                                    "$ref": "#/components/schemas/ParkingLotMemberResponse"
                                }
                            }
                        }
                    }
                }
            }
        },
        "/api/v1/parking-lots/{parkingLotId}/members/{userId}/role": {
            "put": {
                "security": [
                    {
                        "auth-jwt": []
                    }
                ],
                "parameters": [
                    {
                        "name": "parkingLotId",
                        "in": "path",
                        "required": true,
                        "schema": {
                            "type": "string"
                        }
                    },
                    {
                        "name": "userId",
                        "in": "path",
                        "required": true,
                        "schema": {
                            "type": "string"
                        }
                    }
                ],
                "requestBody": {
                    "description": "",
                    "content": {
                        "application/json": {
                            "schema": {
                                "$ref": "#/components/schemas/UpdateMemberRoleRequest"
                            }
                        }
                    }
                },
                "responses": {
                    "200": {
                        "description": "",
                        "content": {
                            "application/json": {
                                "schema": {
                                    "$ref": "#/components/schemas/ParkingLotMemberResponse"
                                }
                            }
                        }
                    }
                }
            }
        },
        "/api/v1/parking-lots/{parkingLotId}/members/{userId}": {
            "delete": {
                "security": [
                    {
                        "auth-jwt": []
                    }
                ],
                "parameters": [
                    {
                        "name": "parkingLotId",
                        "in": "path",
                        "required": true,
                        "schema": {
                            "type": "string"
                        }
                    },
                    {
                        "name": "userId",
                        "in": "path",
                        "required": true,
                        "schema": {
                            "type": "string"
                        }
                    }
                ],
                "responses": {
                    "204": {
                        "description": ""
                    }
                }
            }
        },
        "/api/v1/sessions/open": {
            "get": {
                "summary": "현재 주차 중 목록 조회 (ADMIN 이상)",
                "security": [
                    {
                        "auth-jwt": []
                    }
                ],
                "parameters": [
                    {
                        "name": "parkingLotId",
                        "in": "query",
                        "required": false,
                        "schema": {
                            "type": "string"
                        }
                    }
                ],
                "responses": {
                    "200": {
                        "description": "",
                        "content": {
                            "application/json": {
                                "schema": {
                                    "type": "array",
                                    "items": {
                                        "$ref": "#/components/schemas/SessionResponse"
                                    }
                                }
                            }
                        }
                    }
                }
            }
        },
        "/api/v1/sessions/history": {
            "get": {
                "summary": "날짜별 입출차 기록 조회 (ADMIN 이상)",
                "security": [
                    {
                        "auth-jwt": []
                    }
                ],
                "parameters": [
                    {
                        "name": "parkingLotId",
                        "in": "query",
                        "required": false,
                        "schema": {
                            "type": "string"
                        }
                    },
                    {
                        "name": "date",
                        "in": "query",
                        "required": false,
                        "schema": {
                            "type": "string"
                        }
                    }
                ],
                "responses": {
                    "200": {
                        "description": "",
                        "content": {
                            "application/json": {
                                "schema": {
                                    "type": "array",
                                    "items": {
                                        "$ref": "#/components/schemas/SessionResponse"
                                    }
                                }
                            }
                        }
                    }
                }
            }
        },
        "/api/v1/parking-lots/{parkingLotId}/sessions/current/{plateNumber}": {
            "get": {
                "summary": "번호판으로 현재 세션 조회 (멤버)",
                "security": [
                    {
                        "auth-jwt": []
                    }
                ],
                "parameters": [
                    {
                        "name": "parkingLotId",
                        "in": "path",
                        "required": true,
                        "schema": {
                            "type": "string"
                        }
                    },
                    {
                        "name": "plateNumber",
                        "in": "path",
                        "required": true,
                        "schema": {
                            "type": "string"
                        }
                    }
                ],
                "responses": {
                    "200": {
                        "description": "",
                        "content": {
                            "application/json": {
                                "schema": {
                                    "$ref": "#/components/schemas/SessionResponse"
                                }
                            }
                        }
                    },
                    "404": {
                        "description": ""
                    }
                }
            }
        },
        "/api/v1/vehicles": {
            "post": {
                "summary": "등록 차량 추가 (ADMIN 이상)",
                "security": [
                    {
                        "auth-jwt": []
                    }
                ],
                "requestBody": {
                    "description": "",
                    "content": {
                        "application/json": {
                            "schema": {
                                "$ref": "#/components/schemas/CreateVehicleRequest"
                            }
                        }
                    }
                },
                "responses": {
                    "201": {
                        "description": "",
                        "content": {
                            "application/json": {
                                "schema": {
                                    "$ref": "#/components/schemas/VehicleResponse"
                                }
                            }
                        }
                    }
                }
            },
            "get": {
                "summary": "등록 차량 목록 조회 (멤버)",
                "security": [
                    {
                        "auth-jwt": []
                    }
                ],
                "parameters": [
                    {
                        "name": "parkingLotId",
                        "in": "query",
                        "required": false,
                        "schema": {
                            "type": "string"
                        }
                    }
                ],
                "responses": {
                    "200": {
                        "description": "",
                        "content": {
                            "application/json": {
                                "schema": {
                                    "type": "array",
                                    "items": {
                                        "$ref": "#/components/schemas/VehicleResponse"
                                    }
                                }
                            }
                        }
                    }
                }
            }
        },
        "/api/v1/parking-lots/{parkingLotId}/vehicles/plate/{plateNumber}": {
            "get": {
                "summary": "번호판으로 차량 조회 (멤버)",
                "security": [
                    {
                        "auth-jwt": []
                    }
                ],
                "parameters": [
                    {
                        "name": "parkingLotId",
                        "in": "path",
                        "required": true,
                        "schema": {
                            "type": "string"
                        }
                    },
                    {
                        "name": "plateNumber",
                        "in": "path",
                        "required": true,
                        "schema": {
                            "type": "string"
                        }
                    }
                ],
                "responses": {
                    "200": {
                        "description": "",
                        "content": {
                            "application/json": {
                                "schema": {
                                    "$ref": "#/components/schemas/VehicleResponse"
                                }
                            }
                        }
                    },
                    "404": {
                        "description": ""
                    }
                }
            }
        }
    },
    "components": {
        "schemas": {
            "RegisterRequest": {
                "type": "object",
                "properties": {
                    "email": {
                        "type": "string"
                    },
                    "password": {
                        "type": "string"
                    },
                    "name": {
                        "type": "string"
                    }
                }
            },
            "AuthResponse": {
                "type": "object",
                "properties": {
                    "token": {
                        "type": "string"
                    },
                    "user": {
                        "type": "object",
                        "properties": {
                            "id": {
                                "type": "string"
                            },
                            "email": {
                                "type": "string"
                            },
                            "name": {
                                "type": "string"
                            },
                            "createdAt": {
                                "type": "string"
                            }
                        }
                    }
                }
            },
            "LoginRequest": {
                "type": "object",
                "properties": {
                    "email": {
                        "type": "string"
                    },
                    "password": {
                        "type": "string"
                    }
                }
            },
            "KakaoLoginRequest": {
                "type": "object",
                "properties": {
                    "code": {
                        "type": "string"
                    },
                    "redirectUri": {
                        "type": "string"
                    }
                }
            },
            "UserResponse": {
                "type": "object",
                "properties": {
                    "id": {
                        "type": "string"
                    },
                    "email": {
                        "type": "string"
                    },
                    "name": {
                        "type": "string"
                    },
                    "createdAt": {
                        "type": "string"
                    }
                }
            },
            "GateResponse": {
                "type": "object",
                "properties": {
                    "id": {
                        "type": "integer"
                    },
                    "parkingLotId": {
                        "type": "integer"
                    },
                    "name": {
                        "type": "string"
                    },
                    "deviceKey": {
                        "type": "string"
                    },
                    "direction": {
                        "type": "object",
                        "properties": {
                            "name": {
                                "type": "string"
                            },
                            "ordinal": {
                                "type": "integer"
                            }
                        }
                    }
                }
            },
            "RegisterGateRequest": {
                "type": "object",
                "properties": {
                    "parkingLotId": {
                        "type": "integer"
                    },
                    "name": {
                        "type": "string"
                    },
                    "deviceKey": {
                        "type": "string"
                    },
                    "direction": {
                        "type": "object",
                        "properties": {
                            "name": {
                                "type": "string"
                            },
                            "ordinal": {
                                "type": "integer"
                            }
                        }
                    }
                }
            },
            "PlateDetectedRequest": {
                "type": "object",
                "properties": {
                    "deviceKey": {
                        "type": "string"
                    },
                    "plateNumber": {
                        "type": "string"
                    },
                    "capturedAt": {
                        "type": "string"
                    }
                }
            },
            "PlateDetectedResponse": {
                "type": "object",
                "properties": {
                    "action": {
                        "type": "object",
                        "properties": {
                            "name": {
                                "type": "string"
                            },
                            "ordinal": {
                                "type": "integer"
                            }
                        }
                    },
                    "sessionId": {
                        "type": "integer"
                    },
                    "plateNumber": {
                        "type": "string"
                    },
                    "isRegistered": {
                        "type": "boolean"
                    },
                    "vehicleLabel": {
                        "type": "string"
                    },
                    "vehicleCategory": {
                        "type": "object",
                        "properties": {
                            "name": {
                                "type": "string"
                            },
                            "ordinal": {
                                "type": "integer"
                            }
                        }
                    }
                }
            },
            "CreateParkingLotRequest": {
                "type": "object",
                "properties": {
                    "name": {
                        "type": "string"
                    },
                    "location": {
                        "type": "string"
                    },
                    "isPublic": {
                        "type": "boolean"
                    }
                }
            },
            "ParkingLotResponse": {
                "type": "object",
                "properties": {
                    "id": {
                        "type": "integer"
                    },
                    "name": {
                        "type": "string"
                    },
                    "location": {
                        "type": "string"
                    },
                    "ownerId": {
                        "type": "string"
                    },
                    "isPublic": {
                        "type": "boolean"
                    },
                    "joinCode": {
                        "type": "string"
                    }
                }
            },
            "ParkingLotMemberResponse": {
                "type": "object",
                "properties": {
                    "id": {
                        "type": "integer"
                    },
                    "userId": {
                        "type": "string"
                    },
                    "email": {
                        "type": "string"
                    },
                    "name": {
                        "type": "string"
                    },
                    "role": {
                        "type": "object",
                        "properties": {
                            "name": {
                                "type": "string"
                            },
                            "ordinal": {
                                "type": "integer"
                            }
                        }
                    },
                    "status": {
                        "type": "object",
                        "properties": {
                            "name": {
                                "type": "string"
                            },
                            "ordinal": {
                                "type": "integer"
                            }
                        }
                    },
                    "invitedBy": {
                        "type": "string"
                    },
                    "joinedAt": {
                        "type": "string"
                    }
                }
            },
            "InviteMemberRequest": {
                "type": "object",
                "properties": {
                    "email": {
                        "type": "string"
                    },
                    "role": {
                        "type": "object",
                        "properties": {
                            "name": {
                                "type": "string"
                            },
                            "ordinal": {
                                "type": "integer"
                            }
                        }
                    }
                }
            },
            "UpdateMemberRoleRequest": {
                "type": "object",
                "properties": {
                    "role": {
                        "type": "object",
                        "properties": {
                            "name": {
                                "type": "string"
                            },
                            "ordinal": {
                                "type": "integer"
                            }
                        }
                    }
                }
            },
            "SessionResponse": {
                "type": "object",
                "properties": {
                    "id": {
                        "type": "integer"
                    },
                    "parkingLotId": {
                        "type": "integer"
                    },
                    "plateNumber": {
                        "type": "string"
                    },
                    "vehicleId": {
                        "type": "integer"
                    },
                    "vehicleLabel": {
                        "type": "string"
                    },
                    "vehicleCategory": {
                        "type": "object",
                        "properties": {
                            "name": {
                                "type": "string"
                            },
                            "ordinal": {
                                "type": "integer"
                            }
                        }
                    },
                    "enterGateId": {
                        "type": "integer"
                    },
                    "exitGateId": {
                        "type": "integer"
                    },
                    "enteredAt": {
                        "type": "string"
                    },
                    "exitedAt": {
                        "type": "string"
                    },
                    "status": {
                        "type": "string"
                    }
                }
            },
            "CreateVehicleRequest": {
                "type": "object",
                "properties": {
                    "parkingLotId": {
                        "type": "integer"
                    },
                    "plateNumber": {
                        "type": "string"
                    },
                    "label": {
                        "type": "string"
                    },
                    "category": {
                        "type": "object",
                        "properties": {
                            "name": {
                                "type": "string"
                            },
                            "ordinal": {
                                "type": "integer"
                            }
                        }
                    },
                    "memo": {
                        "type": "string"
                    }
                }
            },
            "VehicleResponse": {
                "type": "object",
                "properties": {
                    "id": {
                        "type": "integer"
                    },
                    "parkingLotId": {
                        "type": "integer"
                    },
                    "plateNumber": {
                        "type": "string"
                    },
                    "label": {
                        "type": "string"
                    },
                    "category": {
                        "type": "object",
                        "properties": {
                            "name": {
                                "type": "string"
                            },
                            "ordinal": {
                                "type": "integer"
                            }
                        }
                    },
                    "memo": {
                        "type": "string"
                    }
                }
            }
        },
        "securitySchemes": {
            "auth-jwt": {
                "type": "http",
                "scheme": "bearer"
            }
        }
    }
}